x402/__init__.py
x402/chains.py
x402/common.py
x402/encoding.py
x402/exact.py
x402/facilitator.py
x402/networks.py
x402/path.py
x402/paywall.py
x402/py.typed
x402/template.py
x402/types.py
x402/clients/__init__.py
x402/clients/base.py
x402/clients/httpx.py
x402/clients/requests.py
x402/fastapi/__init__.py
x402/fastapi/middleware.py
x402/flask/__init__.py
x402/flask/middleware.py
x402/static/paywall.html
og_test_x402-0.0.5.dist-info/METADATA
og_test_x402-0.0.5.dist-info/WHEEL
og_test_x402-0.0.5.dist-info/RECORD
