Metadata-Version: 2.4
Name: og-test-x402
Version: 0.0.5
Summary: x402: An internet native payments protocol
Author-email: erik <erik.reppel@coinbase.com>
License: Apache-2.0
Keywords: cdp,crypto,payments,sdk,web3,x402
Requires-Python: >=3.10
Requires-Dist: eth-account>=0.13.7
Requires-Dist: eth-typing>=4.0.0
Requires-Dist: eth-utils>=3.0.0
Requires-Dist: fastapi[standard]>=0.115.12
Requires-Dist: flask>=3.0.0
Requires-Dist: pydantic-settings>=2.2.1
Requires-Dist: pydantic>=2.10.3
Requires-Dist: python-dotenv>=1.0.1
Requires-Dist: web3>=6.0.0
